segmentation_model_zoo-2025.9.9.dist-info/licenses/LICENSE
smz/__init__.py
smz/layers/__init__.py
smz/layers/condconv.py
smz/layers/conv.py
smz/layers/deformconv.py
smz/layers/moeconv.py
smz/layers/odconv.py
smz/layers/pixelmoe.py
smz/models/SGSNet.py
smz/models/__init__.py
smz/models/emnet.py
smz/models/lkmunet.py
smz/models/monai_zoo.py
smz/models/segmamba.py
smz/models/torchvision_model_zoo.py
smz/models/cotr/CNNBackbone.py
smz/models/cotr/ResTranUnet.py
smz/models/cotr/__init__.py
smz/models/cotr/detrans/DeformableTrans.py
smz/models/cotr/detrans/position_encoding.py
smz/models/cotr/detrans/ops/functions/ms_deform_attn_func.py
smz/models/cotr/detrans/ops/modules/__init__.py
smz/models/cotr/detrans/ops/modules/ms_deform_attn.py
smz/models/dscnet/__init__.py
smz/models/dscnet/dscnet_2d/DSCNet.py
smz/models/dscnet/dscnet_2d/DSCNet_pro.py
smz/models/dscnet/dscnet_2d/DSConv.py
smz/models/dscnet/dscnet_2d/DSConv_pro.py
smz/models/dscnet/dscnet_2d/__init__.py
smz/models/dscnet/dscnet_3d/DSCNet.py
smz/models/dscnet/dscnet_3d/DSConv.py
smz/models/dscnet/dscnet_3d/__init__.py
smz/models/mednext/MedNextV1.py
smz/models/mednext/__init__.py
smz/models/mednext/blocks.py
smz/models/mednext/create_mednext_v1.py
smz/models/mmseg_models/__init__.py
smz/models/mmseg_models/mmseg_model.py
smz/models/mmseg_models/backbones/__init__.py
smz/models/mmseg_models/backbones/biformer.py
smz/models/mmseg_models/backbones/debiformer.py
smz/models/mmseg_models/backbones/samba.py
smz/models/mmseg_models/configs/CCNet/ccnet_r101-d8.py
smz/models/mmseg_models/configs/CCNet/ccnet_r50-d8.py
smz/models/mmseg_models/configs/DeBiFormer/fpn_512_debi_base.py
smz/models/mmseg_models/configs/DeBiFormer/fpn_512_debi_small.py
smz/models/mmseg_models/configs/DeBiFormer/upernet_512_debi_base.py
smz/models/mmseg_models/configs/DeBiFormer/upernet_512_debi_small.py
smz/models/mmseg_models/configs/Samba/upernet_samba.py
smz/models/nnunet/__init__.py
smz/models/nnunet/architectures/unet.py
smz/models/nnunet/building_blocks/plain_conv_encoder.py
segmentation_model_zoo-2025.9.9.dist-info/METADATA
segmentation_model_zoo-2025.9.9.dist-info/WHEEL
segmentation_model_zoo-2025.9.9.dist-info/top_level.txt
segmentation_model_zoo-2025.9.9.dist-info/RECORD
