Metadata-Version: 2.4
Name: segmentation-model-zoo
Version: 2025.9.9
Summary: segmentation-model-zoo
Author-email: jiang yan <1900812927@qq.com>
License: MIT License
Project-URL: homepage, https://gitee.com/Eason596/segmentation-model-zoo
Project-URL: repository, https://gitee.com/Eason596/segmentation-model-zoo
Keywords: deep learning,image segmentation,semantic segmentation,medical image analysis,medical image segmentation
Requires-Python: >=3.10
License-File: LICENSE
Provides-Extra: dev
Dynamic: license-file
